dotprompt/__init__.py
dotprompt/messages.py
dotprompt/prompt.py
dotprompt/types.py
python_dotprompt-0.0.2.dist-info/LICENSE
python_dotprompt-0.0.2.dist-info/METADATA
python_dotprompt-0.0.2.dist-info/WHEEL
python_dotprompt-0.0.2.dist-info/RECORD
