Metadata-Version: 2.1
Name: python-dotprompt
Version: 0.0.2
Summary: dotprompt for your prompt prompt needs
License: MIT
Author: prompty.prompt
Author-email: promptly@dotprompt.dev
Requires-Python: >=3.12,<4.0
Classifier: License :: OSI Approved :: MIT License
Classifier: Programming Language :: Python :: 3
Classifier: Programming Language :: Python :: 3.12
Requires-Dist: jinja2 (>=3.1.4,<4.0.0)
